MANIFEST.in
README.rst
setup.py
docs/HISTORY.rst
docs/LICENSE.txt
seantis/__init__.py
seantis.plonetools.egg-info/PKG-INFO
seantis.plonetools.egg-info/SOURCES.txt
seantis.plonetools.egg-info/dependency_links.txt
seantis.plonetools.egg-info/entry_points.txt
seantis.plonetools.egg-info/namespace_packages.txt
seantis.plonetools.egg-info/not-zip-safe
seantis.plonetools.egg-info/requires.txt
seantis.plonetools.egg-info/top_level.txt
seantis/plonetools/__init__.py
seantis/plonetools/allkeys.txt
seantis/plonetools/async.py
seantis/plonetools/configure.zcml
seantis/plonetools/pyuca.py
seantis/plonetools/schemafields.py
seantis/plonetools/setuphandlers.py
seantis/plonetools/sync.sh
seantis/plonetools/testing.py
seantis/plonetools/testlayer.py
seantis/plonetools/tools.py
seantis/plonetools/unrestricted.py
seantis/plonetools/behaviors/__init__.py
seantis/plonetools/behaviors/customtitle.py
seantis/plonetools/browser/__init__.py
seantis/plonetools/browser/baseform.py
seantis/plonetools/browser/basegroup.py
seantis/plonetools/browser/baseview.py
seantis/plonetools/browser/shared.py
seantis/plonetools/js/URI.js
seantis/plonetools/js/dependencies.js
seantis/plonetools/locales/seantis.plonetools.pot
seantis/plonetools/locales/de/LC_MESSAGES/seantis.plonetools.po
seantis/plonetools/profiles/default/jsregistry.xml
seantis/plonetools/profiles/default/metadata.xml
seantis/plonetools/scripts/configure-email.py
seantis/plonetools/scripts/install-memcached-sessions.py
seantis/plonetools/tests/__init__.py
seantis/plonetools/tests/test_async.py
seantis/plonetools/tests/test_baseform.py
seantis/plonetools/tests/test_behaviors.py
seantis/plonetools/tests/test_schemafields.py
seantis/plonetools/tests/test_tools.py