Metadata-Version: 1.1
Name: seantis.plonetools
Version: 0.14
Summary: A collection of tools shared with different Seantis Plone modules.
Home-page: https://github.com/seantis/seantis.plonetools
Author: Seantis GmbH
Author-email: info@seantis.ch
License: GPL v2
Keywords: plone seantis tools utilities
Platform: UNKNOWN
Classifier: Framework :: Plone
Classifier: Framework :: Plone :: 4.3
Classifier: Intended Audience :: Developers
Classifier: Topic :: Software Development :: Libraries :: Python Modules
Classifier: Programming Language :: Python
